winrt_windows_app_sdk/__init__.py
winrt_windows_app_sdk/cppwinrt/winrt/Microsoft.Graphics.DirectX.h
winrt_windows_app_sdk/cppwinrt/winrt/Microsoft.Graphics.Display.h
winrt_windows_app_sdk/cppwinrt/winrt/Microsoft.Graphics.Imaging.h
winrt_windows_app_sdk/cppwinrt/winrt/Microsoft.Security.Authentication.OAuth.h
winrt_windows_app_sdk/cppwinrt/winrt/Microsoft.UI.Composition.Core.h
winrt_windows_app_sdk/cppwinrt/winrt/Microsoft.UI.Composition.Diagnostics.h
winrt_windows_app_sdk/cppwinrt/winrt/Microsoft.UI.Composition.Effects.h
winrt_windows_app_sdk/cppwinrt/winrt/Microsoft.UI.Composition.Interactions.h
winrt_windows_app_sdk/cppwinrt/winrt/Microsoft.UI.Composition.Scenes.h
winrt_windows_app_sdk/cppwinrt/winrt/Microsoft.UI.Composition.SystemBackdrops.h
winrt_windows_app_sdk/cppwinrt/winrt/Microsoft.UI.Composition.h
winrt_windows_app_sdk/cppwinrt/winrt/Microsoft.UI.Content.h
winrt_windows_app_sdk/cppwinrt/winrt/Microsoft.UI.Dispatching.h
winrt_windows_app_sdk/cppwinrt/winrt/Microsoft.UI.Input.DragDrop.h
winrt_windows_app_sdk/cppwinrt/winrt/Microsoft.UI.Input.Interop.h
winrt_windows_app_sdk/cppwinrt/winrt/Microsoft.UI.Input.h
winrt_windows_app_sdk/cppwinrt/winrt/Microsoft.UI.System.h
winrt_windows_app_sdk/cppwinrt/winrt/Microsoft.UI.Text.h
winrt_windows_app_sdk/cppwinrt/winrt/Microsoft.UI.Windowing.h
winrt_windows_app_sdk/cppwinrt/winrt/Microsoft.UI.Xaml.Automation.Peers.h
winrt_windows_app_sdk/cppwinrt/winrt/Microsoft.UI.Xaml.Automation.Provider.h
winrt_windows_app_sdk/cppwinrt/winrt/Microsoft.UI.Xaml.Automation.Text.h
winrt_windows_app_sdk/cppwinrt/winrt/Microsoft.UI.Xaml.Automation.h
winrt_windows_app_sdk/cppwinrt/winrt/Microsoft.UI.Xaml.Controls.AnimatedVisuals.h
winrt_windows_app_sdk/cppwinrt/winrt/Microsoft.UI.Xaml.Controls.Primitives.h
winrt_windows_app_sdk/cppwinrt/winrt/Microsoft.UI.Xaml.Controls.h
winrt_windows_app_sdk/cppwinrt/winrt/Microsoft.UI.Xaml.Data.h
winrt_windows_app_sdk/cppwinrt/winrt/Microsoft.UI.Xaml.Documents.h
winrt_windowsappsdk-3.2.1.dist-info/METADATA
winrt_windowsappsdk-3.2.1.dist-info/WHEEL
winrt_windowsappsdk-3.2.1.dist-info/top_level.txt
winrt_windowsappsdk-3.2.1.dist-info/RECORD
